{
    "Ar36": {
        "error": 0.00022219499331088,
        "error_type": "SEM",
        "filter_outliers_dict": {
            "filter_outliers": true,
            "iterations": 1,
            "std_devs": 3,
            "use_iqr_filtering": false,
            "use_standard_deviation_filtering": false
        },
        "fit": "linear",
        "fn": 339,
        "include_baseline_error": false,
        "n": 340,
        "outlier_excluded": [
            315
        ],
        "reviewed": true,
        "user_excluded": [],
        "value": 0.01780097468732345
    },
    "Ar37": {
        "error": 0.015931080712136215,
        "error_type": "SEM",
        "filter_outliers_dict": {
            "filter_outliers": true,
            "iterations": 1,
            "std_devs": 3,
            "use_iqr_filtering": false,
            "use_standard_deviation_filtering": false
        },
        "fit": "linear",
        "fn": 338,
        "include_baseline_error": false,
        "n": 340,
        "outlier_excluded": [
            267,
            172
        ],
        "reviewed": true,
        "user_excluded": [],
        "value": -0.10500606280666744
    },
    "Ar38": {
        "error": 0.005333938614005573,
        "error_type": "SEM",
        "filter_outliers_dict": {
            "filter_outliers": true,
            "iterations": 1,
            "std_devs": 3,
            "use_iqr_filtering": false,
            "use_standard_deviation_filtering": false
        },
        "fit": "linear",
        "fn": 338,
        "include_baseline_error": false,
        "n": 340,
        "outlier_excluded": [
            334,
            207
        ],
        "reviewed": true,
        "user_excluded": [],
        "value": 0.28762524593923533
    },
    "Ar39": {
        "error": 0.010343050534573857,
        "error_type": "SEM",
        "filter_outliers_dict": {
            "filter_outliers": true,
            "iterations": 1,
            "std_devs": 3,
            "use_iqr_filtering": false,
            "use_standard_deviation_filtering": false
        },
        "fit": "linear",
        "fn": 340,
        "include_baseline_error": false,
        "n": 340,
        "outlier_excluded": [],
        "reviewed": true,
        "user_excluded": [],
        "value": 33.80171815584475
    },
    "Ar40": {
        "error": 0.05345307690005535,
        "error_type": "SEM",
        "filter_outliers_dict": {
            "filter_outliers": true,
            "iterations": 1,
            "std_devs": 3,
            "use_iqr_filtering": false,
            "use_standard_deviation_filtering": false
        },
        "fit": "parabolic",
        "fn": 340,
        "include_baseline_error": false,
        "n": 340,
        "outlier_excluded": [],
        "reviewed": true,
        "user_excluded": [],
        "value": 229.84432689358368
    }
}